CHANGELOG.txt
LICENSE.txt
MANIFEST.in
README.txt
setup.py
pyHPump/__init__.py
pyHPump/command.py
pyHPump/commandPSD4.py
pyHPump/commandPSD4SmoothFlow.py
pyHPump/commandPSD6.py
pyHPump/commandPSD6SmoothFlow.py
pyHPump/communication.py
pyHPump/psd.py
pyHPump/util.py
pyHPump.egg-info/PKG-INFO
pyHPump.egg-info/SOURCES.txt
pyHPump.egg-info/dependency_links.txt
pyHPump.egg-info/requires.txt
pyHPump.egg-info/top_level.txt