Metadata-Version: 1.1
Name: pyHPump
Version: 2.0.0
Summary: basic pump application
Home-page: UNKNOWN
Author: Camil Milos
Author-email: mcamil16@yahoo.com
License: MIT
Keywords: psd
Platform: UNKNOWN
Classifier: Development Status :: 5 - Production/Stable
Classifier: Intended Audience :: Education
Classifier: Operating System :: Microsoft :: Windows :: Windows 10
Classifier: License :: OSI Approved :: MIT License
Classifier: Programming Language :: Python :: 3
